form_error_reporting.py
django_form_error_reporting-0.12.dist-info/LICENSE.txt
django_form_error_reporting-0.12.dist-info/METADATA
django_form_error_reporting-0.12.dist-info/WHEEL
django_form_error_reporting-0.12.dist-info/top_level.txt
django_form_error_reporting-0.12.dist-info/RECORD
